lazyhooks/__init__.py
lazyhooks/exceptions.py
lazyhooks/monitoring.py
lazyhooks/presets.py
lazyhooks/py.typed
lazyhooks/receiver.py
lazyhooks/sender.py
lazyhooks/sync.py
lazyhooks/storage/__init__.py
lazyhooks/storage/base.py
lazyhooks/storage/memory.py
lazyhooks/storage/redis.py
lazyhooks/storage/sqlite.py
lazyhooks/testing/__init__.py
lazyhooks/testing/fixtures.py
lazyhooks-0.2.3.dist-info/licenses/LICENSE
lazyhooks-0.2.3.dist-info/METADATA
lazyhooks-0.2.3.dist-info/WHEEL
lazyhooks-0.2.3.dist-info/top_level.txt
lazyhooks-0.2.3.dist-info/RECORD
