Metadata-Version: 2.4
Name: lazyhooks
Version: 0.2.3
Summary: A lightweight, resilient webhook sender and receiver.
Author-email: Stacktactician <mmmoyosore09@gmail.com>
License: MIT
Project-URL: Homepage, https://github.com/StackTactician/LazyHooks
Keywords: webhooks,asyncio,persistence,networking
Classifier: Development Status :: 3 - Alpha
Classifier: Intended Audience :: Developers
Classifier: License :: OSI Approved :: MIT License
Classifier: Programming Language :: Python :: 3
Classifier: Programming Language :: Python :: 3.8
Classifier: Programming Language :: Python :: 3.9
Classifier: Programming Language :: Python :: 3.10
Classifier: Programming Language :: Python :: 3.11
Classifier: Programming Language :: Python :: 3.12
Classifier: Topic :: Internet :: WWW/HTTP
Classifier: Framework :: AsyncIO
Requires-Python: >=3.8
License-File: LICENSE
Requires-Dist: aiohttp>=3.8.0
Provides-Extra: dev
Requires-Dist: pytest; extra == "dev"
Requires-Dist: pytest-asyncio; extra == "dev"
Requires-Dist: mypy; extra == "dev"
Requires-Dist: redis; extra == "dev"
Provides-Extra: redis
Requires-Dist: redis>=4.2.0; extra == "redis"
Provides-Extra: prometheus
Requires-Dist: prometheus-client; extra == "prometheus"
Provides-Extra: sentry
Requires-Dist: sentry-sdk; extra == "sentry"
Provides-Extra: structlog
Requires-Dist: structlog; extra == "structlog"
Provides-Extra: testing
Requires-Dist: responses; extra == "testing"
Provides-Extra: full
Requires-Dist: redis>=4.2.0; extra == "full"
Requires-Dist: prometheus-client; extra == "full"
Requires-Dist: sentry-sdk; extra == "full"
Requires-Dist: structlog; extra == "full"
Requires-Dist: responses; extra == "full"
Dynamic: license-file
